<annotation verified="yes">
	<folder>undrawn</folder>
	<filename>IMG_20191021_212323.jpg</filename>
	<path>C:\Users\Mark\Desktop\Chapstick\undrawn\IMG_20191021_212323.jpg</path>
	<source>
		<database>Unknown</database>
	</source>
	<size>
		<width>960</width>
		<height>960</height>
		<depth>3</depth>
	</size>
	<segmented>0</segmented>
	<object>
		<name>chapstick</name>
		<pose>Unspecified</pose>
		<truncated>0</truncated>
		<difficult>0</difficult>
		<bndbox>
			<xmin>447</xmin>
			<ymin>380</ymin>
			<xmax>684</xmax>
			<ymax>792</ymax>
		</bndbox>
	</object>
</annotation>
